taichu_websocket/__init__.py
taichu_websocket/client.py
taichu_websocket/server.py
taichu_websocket-0.2.0.dist-info/METADATA
taichu_websocket-0.2.0.dist-info/WHEEL
taichu_websocket-0.2.0.dist-info/top_level.txt
taichu_websocket-0.2.0.dist-info/RECORD
