Metadata-Version: 2.4
Name: taichu_websocket
Version: 0.2.0
Summary: 一个灵活的 WebSocket 服务器库，支持自定义处理逻辑
Author-email: taichugolden <taichugolden@outlook.com>
License-Expression: MIT
Project-URL: Homepage, https://github.com/TaichuGolden/taichu_websocket
Requires-Python: >=3.6
Requires-Dist: websockets
